cdiscountapi/__init__.py
cdiscountapi/cdiscountapi.py
cdiscountapi/exceptions.py
cdiscountapi/helpers.py
cdiscountapi/assets/config.yaml
cdiscountapi/assets/offer.json
cdiscountapi/packages/__init__.py
cdiscountapi/packages/validator.py
cdiscountapi/packages/offer_package/[Content_Types].xml
cdiscountapi/packages/offer_package/Content/Offers.xml
cdiscountapi/packages/offer_package/_rels/.rels
cdiscountapi/packages/product_package/[Content_Types].xml
cdiscountapi/packages/product_package/Content/Products.xml
cdiscountapi/packages/product_package/_rels/.rels
cdiscountapi/sections/__init__.py
cdiscountapi/sections/base.py
cdiscountapi/sections/discussions.py
cdiscountapi/sections/fulfillment.py
cdiscountapi/sections/offers.py
cdiscountapi/sections/orders.py
cdiscountapi/sections/products.py
cdiscountapi/sections/relays.py
cdiscountapi/sections/sandbox.py
cdiscountapi/sections/seller.py
cdiscountapi/sections/webmail.py
cdiscountapi/templates/Offers.xml
cdiscountapi/templates/Products.xml
cdiscountapi-0.2.2.dist-info/LICENSE
cdiscountapi-0.2.2.dist-info/WHEEL
cdiscountapi-0.2.2.dist-info/METADATA
cdiscountapi-0.2.2.dist-info/RECORD
