Metadata-Version: 2.1
Name: cdiscountapi
Version: 0.2.2
Summary: cdiscountapi is a wrapper around the Cdiscount Marketplace API
Author: ZIBOURA Mathilde, RABOIS Damien, Nicolas Baccelli
Author-email: nicolas.baccelli@abc-culture.fr
Requires-Python: >=3.6
Classifier: License :: OSI Approved :: MIT License
Requires-Dist: requests>=2.26.0
Requires-Dist: requests_mock>=1.9.3
Requires-Dist: zeep>=4.1.0
Requires-Dist: dicttoxml>=1.7.4
Requires-Dist: PyYAML>=6.0
Requires-Dist: jinja2>=3.0.3
Requires-Dist: pdbpp ; extra == "dev"
Requires-Dist: ipython ; extra == "dev"
Requires-Dist: konch ; extra == "dev"
Requires-Dist: pandas ; extra == "dev"
Requires-Dist: sphinx ; extra == "doc"
Requires-Dist: sphinx-nameko-theme ; extra == "doc"
Requires-Dist: pytest>=6.2.5 ; extra == "test"
Requires-Dist: vcrpy>=4.1.1 ; extra == "test"
Requires-Dist: pytest-vcr>=1.0.2 ; extra == "test"
Requires-Dist: coverage>=6.1.2 ; extra == "test"
Requires-Dist: pytest-cov>=3.0.0 ; extra == "test"
Provides-Extra: dev
Provides-Extra: doc
Provides-Extra: test
